Metadata-Version: 2.1
Name: newunicfolder
Version: 0.0.1
Summary: My Package
Author: ktrnkplv
Author-email: eduardovna.ek@mail.ru
